infragraph/__init__.py
infragraph/infragraph.py
infragraph/infragraph_pb2.py
infragraph/infragraph_pb2_grpc.py
infragraph/infragraph_service.py
infragraph/blueprints/devices/cx5.py
infragraph/blueprints/devices/dgx.py
infragraph/blueprints/devices/generic_switch.py
infragraph/blueprints/devices/ironwood_rack.py
infragraph/blueprints/devices/server.py
infragraph/blueprints/fabrics/clos_fat_tree_fabric.py
infragraph/blueprints/fabrics/closfabric.py
infragraph/blueprints/fabrics/single_tier_fabric.py
infragraph/docs/infragraph.proto
infragraph/docs/openapi.json
infragraph/docs/openapi.yaml
infragraph/docs/requirements.txt
infragraph/tests/conftest.py
infragraph/tests/test_infrastructure.py
infragraph/tests/test_ipaddress_annotations.py
infragraph/tests/test_rank_annotations.py
infragraph/tests/test_shortest_path.py
infragraph/tests/test_blueprints/test_clos_fat_tree_fabric.py
infragraph/tests/test_blueprints/test_devices.py
infragraph/tests/test_blueprints/test_single_tier_fabric.py
infragraph-0.6.2.dist-info/METADATA
infragraph-0.6.2.dist-info/WHEEL
infragraph-0.6.2.dist-info/licenses/LICENSE
infragraph-0.6.2.dist-info/RECORD
