Metadata-Version: 2.4
Name: infragraph
Version: 0.6.2
Summary: Infrastructure as a Graph
Project-URL: Homepage, https://infragraph.dev/
Project-URL: Repository, https://github.com/Keysight/infragraph
Author-email: TBD <tbd@infragraph.org>
License: MIT
License-File: LICENSE
Keywords: astrasim,chakra,graph,infrastructure
Classifier: License :: OSI Approved :: MIT License
Classifier: Operating System :: OS Independent
Classifier: Programming Language :: Python :: 3
Requires-Python: >=3.8
Requires-Dist: grpcio
Requires-Dist: networkx
Requires-Dist: protobuf
Requires-Dist: pyyaml
Requires-Dist: requests
Requires-Dist: semantic-version
